setup.py
brynq_sdk_leapsome/__init__.py
brynq_sdk_leapsome/api_interface.py
brynq_sdk_leapsome/sftp_interface.py
brynq_sdk_leapsome.egg-info/PKG-INFO
brynq_sdk_leapsome.egg-info/SOURCES.txt
brynq_sdk_leapsome.egg-info/dependency_links.txt
brynq_sdk_leapsome.egg-info/not-zip-safe
brynq_sdk_leapsome.egg-info/requires.txt
brynq_sdk_leapsome.egg-info/top_level.txt