Metadata-Version: 1.0
Name: brynq-sdk-leapsome
Version: 1.0.9
Summary: Leapsome wrapper from BrynQ
Home-page: UNKNOWN
Author: BrynQ
Author-email: support@brynq.com
License: BrynQ License
Platform: UNKNOWN
